cryptoino/__init__.py
cryptoino/cryptoino.py
cryptoino/examples.py
cryptoino-0.5.0.dist-info/LICENSE.md
cryptoino-0.5.0.dist-info/METADATA
cryptoino-0.5.0.dist-info/WHEEL
cryptoino-0.5.0.dist-info/top_level.txt
cryptoino-0.5.0.dist-info/RECORD
