Metadata-Version: 2.1
Name: cryptoino
Version: 0.5.0
Summary: cryptocurrencies information from coingecko
Home-page: https://github.com/amirkho-py/cryptoino
Author: Amirhossein Khosravi
Author-email: me@amirkho.ir
License: MIT
Keywords: cryptoino,coingecko,crypto info,crypto price,cryptocurrencies
Platform: UNKNOWN
Classifier: Programming Language :: Python :: 3.7
Classifier: Programming Language :: Python :: 3.8
Classifier: Programming Language :: Python :: 3.10
License-File: LICENSE.md
Requires-Dist: requests
